Metadata-Version: 2.1
Name: torchtmageclass
Version: 0.0.1
Summary: A library for image classification using PyTorch.
Home-page: https://github.com/DiogoBrazil/lib-to-class-image-with-pytorch.git
Author: Diogo Ribeiro
Author-email: diogoifroads@gmail.com
License: MIT
Keywords: pytorch,deep-learning,image-classification,machine-learning,computer-vision,classification,torch,TorchImageClass,neural-networks,cnn,transfer-learning
Platform: UNKNOWN
Requires-Python: >=3.9
License-File: LICENCE
